Workbook

Sheet 935
A1: 2000單內排名 | B1: 單字 | C1: KK音標 | D1: 中譯 | E1: 例句 | F1: 翻譯 | G1: 出現次數（歷年加總） | H1: 出現年份數 | I1: 出現年份（民國） | J1: 佔總詞頻% | K1: 累積詞頻% | L1: CEFR難度 | M1: 2000單級別 | N1: 中譯 | O1: 主題分類 | P1: 核心300 | Q1: 鞏固450
A2: 1 | B2: person | C2: =IFERROR(_xlfn.XLOOKUP(B2,'2000'!A:A,'2000'!B:B),"") -> ˈpɝsn | D2: (n.) 人 | E2: He is a very nice person. | F2: 他是個很客氣的人。 | G2: 188 | H2: 10 | I2: 105、106、107、108、109、110、111、112、113、114 | J2: 1.314 | K2: 1.31 | L2: A2 | M2: 1200單 | N2: (n.) 人 | O2: People | P2: ✓
A3: 2 | B3: about | C3: =IFERROR(_xlfn.XLOOKUP(B3,'2000'!A:A,'2000'!B:B),"") -> əˈbaʊt | D3: (prep.) 有關 | E3: This book is about history. | F3: 這本書是關於歷史的。 | G3: 177 | H3: 10 | I3: 105、106、107、108、109、110、111、112、113、114 | J3: 1.237 | K3: 2.55 | L3: 未分類 | M3: 1200單 | N3: (prep.) 有關 | O3: Prepositions | P3: ✓
A4: 3 | B4: from | C4: =IFERROR(_xlfn.XLOOKUP(B4,'2000'!A:A,'2000'!B:B),"") -> frʌm | D4: (prep.) 從… | E4: She is from Canada. | F4: 她來自加拿大。 | G4: 148 | H4: 10 | I4: 105、106、107、108、109、110、111、112、113、114 | J4: 1.034 | K4: 3.59 | L4: 未分類 | M4: 1200單 | N4: (prep.) 從… | O4: Prepositions | P4: ✓
A5: 4 | B5: with | C5: =IFERROR(_xlfn.XLOOKUP(B5,'2000'!A:A,'2000'!B:B),"") -> wɪð | D5: (prep.) 有；用 | E5: She walked into the room with a smile. | F5: 她帶著微笑走進房間。 | G5: 142 | H5: 10 | I5: 105、106、107、108、109、110、111、112、113、114 | J5: 0.992 | K5: 4.58 | L5: 未分類 | M5: 1200單 | N5: (prep.) 有；用 | O5: Prepositions | P5: ✓
A6: 5 | B6: good | C6: =IFERROR(_xlfn.XLOOKUP(B6,'2000'!A:A,'2000'!B:B),"") -> ɡʊd | D6: (adj.) 好的 | E6: This restaurant serves good food. | F6: 這家餐廳的食物很好吃。 | G6: 135 | H6: 10 | I6: 105、106、107、108、109、110、111、112、113、114 | J6: 0.944 | K6: 5.52 | L6: A1 | M6: 1200單 | N6: (adj.) 好的 | O6: Personal characteristics | P6: ✓
A7: 6 | B7: get | C7: =IFERROR(_xlfn.XLOOKUP(B7,'2000'!A:A,'2000'!B:B),"") -> ɡɛt | D7: (v.) 得到 | E7: I need to get some groceries from the store. | F7: 我需要從商店買些雜貨。 | G7: 131 | H7: 10 | I7: 105、106、107、108、109、110、111、112、113、114 | J7: 0.916 | K7: 6.44 | L7: 未分類 | M7: 1200單 | N7: (v.) 得到 | O7: Other verbs | P7: ✓
A8: 7 | B8: time | C8: =IFERROR(_xlfn.XLOOKUP(B8,'2000'!A:A,'2000'!B:B),"") -> taɪm | D8: (n.) 時間 | E8: Time flies when you’re having fun. | F8: 快樂的時光總是飛逝。 | G8: 101 | H8: 10 | I8: 105、106、107、108、109、110、111、112、113、114 | J8: 0.706 | K8: 7.14 | L8: A1 | M8: 1200單 | N8: (n.) 時間 | O8: Time | P8: ✓
A9: 8 | B9: city | C9: =IFERROR(_xlfn.XLOOKUP(B9,'2000'!A:A,'2000'!B:B),"") -> ˈsɪtɪ | D9: (n.) 城市 | E9: New York is a bustling city. | F9: 紐約是一個繁忙的城市。 | G9: 97 | H9: 9 | I9: 105、106、107、108、109、110、112、113、114 | J9: 0.678 | K9: 7.82 | L9: A1 | M9: 1200單 | N9: (n.) 城市 | O9: Places-locations | P9: ✓
A10: 9 | B10: think | C10: =IFERROR(_xlfn.XLOOKUP(B10,'2000'!A:A,'2000'!B:B),"") -> θɪŋk | D10: (v.) 想 | E10: I think it’s going to rain today. | F10: 我認為今天會下雨。 | G10: 94 | H10: 10 | I10: 105、106、107、108、109、110、111、112、113、114 | J10: 0.657 | K10: 8.48 | L10: 未分類 | M10: 800單 | N10: (v.) 認為；思考 | O10: Other nouns | P10: ✓
A11: 10 | B11: know | C11: =IFERROR(_xlfn.XLOOKUP(B11,'2000'!A:A,'2000'!B:B),"") -> no | D11: (v.) 知道 | E11: Do you know where the nearest gas station is? | F11: 你知道最近的加油站在哪裡嗎？ | G11: 84 | H11: 10 | I11: 105、106、107、108、109、110、111、112、113、114 | J11: 0.587 | K11: 9.06 | L11: A1 | M11: 1200單 | N11: (v.) 知道 | O11: Other verbs | P11: ✓
A12: 11 | B12: work | C12: =IFERROR(_xlfn.XLOOKUP(B12,'2000'!A:A,'2000'!B:B),"") -> wɝk | D12: (v.) 工作 | E12: She works at a bank. | F12: 她在銀行工作。 | G12: 83 | H12: 10 | I12: 105、106、107、108、109、110、111、112、113、114 | J12: 0.58 | K12: 9.64 | L12: A1 | M12: 1200單 | N12: (v.) 工作 | O12: Occupations | P12: ✓
A13: 12 | B13: say | C13: =IFERROR(_xlfn.XLOOKUP(B13,'2000'!A:A,'2000'!B:B),"") -> se | D13: (v.) 說 | E13: What did he say to you? | F13: 他對你說了什麼？ | G13: 79 | H13: 10 | I13: 105、106、107、108、109、110、111、112、113、114 | J13: 0.552 | K13: 10.2 | L13: 未分類 | M13: 1200單 | N13: (v.) 說 | O13: School | P13: ✓
... A70: 69 | B70: right | C70: =IFERROR(_xlfn.XLOOKUP(B70,'2000'!A:A,'2000'!B:B),"") -> raɪt | D70: (adj.) 正確的 | E70: You are absolutely right. | F70: 你完全正確。 | G70: 32 | H70: 10 | I70: 105、106、107、108、109、110、111、112、113、114 | J70: 0.224 | K70: 30.44 | L70: A1 | M70: 1200單 | N70: (adj.) 正確的 | O70: Places-locations | P70: ✓
A71: 70 | B71: train | C71: =IFERROR(_xlfn.XLOOKUP(B71,'2000'!A:A,'2000'!B:B),"") -> tren | D71: (n.) 訓練 | E71: She is training for the marathon. | F71: 她正在為馬拉松訓練。 | G71: 32 | H71: 4 | I71: 109110111114 | J71: 0.224 | K71: 30.66 | L71: 未分類 | M71: 1200單 | N71: (n.) 火車；(v.) 訓練 | O71: Transportation | P71: ✓
A72: 71 | B72: well | C72: =IFERROR(_xlfn.XLOOKUP(B72,'2000'!A:A,'2000'!B:B),"") -> wɛl | D72: (adv.) 很好地 | E72: She sings very well. | F72: 她唱得很好。 | G72: 31 | H72: 9 | I72: 105、106、107、108、109、110、111、112、113 | J72: 0.217 | K72: 30.88 | L72: 未分類 | M72: 1200單 | N72: (adv.) 很好地 | O72: Health | P72: ✓
A73: 72 | B73: visit | C73: =IFERROR(_xlfn.XLOOKUP(B73,'2000'!A:A,'2000'!B:B),"") -> ˈvɪzɪt | D73: (v.) 探訪 | E73: We plan to visit our grandparents next week. | F73: 我們計劃下週探望祖父母。 | G73: 31 | H73: 10 | I73: 105、106、107、108、109、110、111、112、113、114 | J73: 0.217 | K73: 31.09 | L73: A2 | M73: 1200單 | N73: (v.) 探訪 | O73: Other verbs | P73: ✓
A74: 73 | B74: bring | C74: =IFERROR(_xlfn.XLOOKUP(B74,'2000'!A:A,'2000'!B:B),"") -> brɪŋ | D74: (v.) 帶來 | E74: Bring me that book, please. | F74: 請把那本書拿給我。 | G74: 31 | H74: 8 | I74: 105、106、107、108、109、112、113、114 | J74: 0.217 | K74: 31.31 | L74: A1 | M74: 1200單 | N74: (v.) 帶來 | O74: Other verbs | P74: ✓
A75: 74 | B75: decide | C75: =IFERROR(_xlfn.XLOOKUP(B75,'2000'!A:A,'2000'!B:B),"") -> dɪˈsaɪd | D75: (v.) 決定 | E75: I decided to take a vacation next month. | F75: 我決定下個月休假。 | G75: 31 | H75: 10 | I75: 105、106、107、108、109、110、111、112、113、114 | J75: 0.217 | K75: 31.53 | L75: A2 | M75: 1200單 | N75: (v.) 決定 | O75: Other verbs | P75: ✓
A76: 75 | B76: however | C76: =IFERROR(_xlfn.XLOOKUP(B76,'2000'!A:A,'2000'!B:B),"") -> haʊˈɛvɚ | D76: (adv.) 然而 | E76: However, we still have a lot of work to do. | F76: 然而，我們仍然有很多工作要做。 | G76: 31 | H76: 10 | I76: 105、106、107、108、109、110、111、112、113、114 | J76: 0.217 | K76: 31.74 | L76: A2 | M76: 1200單 | N76: (adv.) 然而 | O76: Conjunctions | P76: ✓
A77: 76 | B77: teacher | C77: =IFERROR(_xlfn.XLOOKUP(B77,'2000'!A:A,'2000'!B:B),"") -> ˈtitʃɚ | D77: (n.) 老師 | E77: My teacher is very kind and patient. | F77: 我的老師非常善良且有耐心。 | G77: 31 | H77: 4 | I77: 107110111113 | J77: 0.217 | K77: 31.96 | L77: A2 | M77: 1200單 | N77: (n.) 老師；教師 | O77: School | P77: ✓
A78: 77 | B78: weekend | C78: =IFERROR(_xlfn.XLOOKUP(B78,'2000'!A:A,'2000'!B:B),"") -> ˈwikˌɛnd | D78: (n.) 週末 | E78: We went hiking last weekend. | F78: 上週末我們去遠足了。 | G78: 31 | H78: 5 | I78: 108110112113114 | J78: 0.217 | K78: 32.18 | L78: A2 | M78: 1200單 | N78: (n.) 週末 | O78: Time | P78: ✓
A79: 78 | B79: popular | C79: =IFERROR(_xlfn.XLOOKUP(B79,'2000'!A:A,'2000'!B:B),"") -> ˈpɑpjʊlɚ | D79: (adj.) 受歡迎的 | E79: This song is very popular among teenagers. | F79: 這首歌在青少年中非常受歡迎。 | G79: 30 | H79: 9 | I79: 105、106、107、108、109、111、112、113、114 | J79: 0.21 | K79: 32.39 | L79: A1 | M79: 1200單 | N79: (adj.) 受歡迎的 | O79: Other adjectives | P79: ✓
A80: 79 | B80: second | C80: =IFERROR(_xlfn.XLOOKUP(B80,'2000'!A:A,'2000'!B:B),"") -> ˈsɛkənd | D80: (adj.) 第二的 | E80: He came in second place in the race. | F80: 他在比賽中獲得第二名。 | G80: 30 | H80: 9 | I80: 105、106、107、108、109、111、112、113、114 | J80: 0.21 | K80: 32.6 | L80: A1 | M80: 1200單 | N80: (adj.) 第二的 | O80: Time | P80: ✓
A81: 80 | B81: water | C81: =IFERROR(_xlfn.XLOOKUP(B81,'2000'!A:A,'2000'!B:B),"") -> ˈwɔtɚ | D81: (n.) 水 | E81: Drink plenty of water every day. | F81: 每天多喝水。 | G81: 30 | H81: 9 | I81: 105、106、107、108、109、110、111、112、114 | J81: 0.21 | K81: 32.81 | L81: A1 | M81: 1200單 | N81: (n.) 水 | O81: Food & drinks | P81: ✓
A82: 81 | B82: likely | C82: =IFERROR(_xlfn.XLOOKUP(B82,'2000'!A:A,'2000'!B:B),"") -> ˈlaɪklɪ | D82: (adv.) 可能 | E82: It’s likely to rain tomorrow. | F82: 明天可能會下雨。 | G82: 30 | H82: 8 | I82: 105、106、107、108、110、111、113、114 | J82: 0.21 | K82: 33.02 | L82: 未分類 | M82: 800單 | N82: (adj.) 可能的 | O82: Other adjectives | P82: ✓
A83: 82 | B83: try | C83: =IFERROR(_xlfn.XLOOKUP(B83,'2000'!A:A,'2000'!B:B),"") -> traɪ | D83: (v.) 試圖 | E83: I’ll try my best to finish the project on time. | F83: 我會盡力按時完成這個項目。 | G83: 30 | H83: 10 | I83: 105、106、107、108、109、110、111、112、113、114 | J83: 0.21 | K83: 33.23 | L83: A1 | M83: 1200單 | N83: (v.) 試圖 | O83: Other verbs | P83: ✓
A84: 83 | B84: news | C84: =IFERROR(_xlfn.XLOOKUP(B84,'2000'!A:A,'2000'!B:B),"") -> njuz | D84: (n.) 新聞 | E84: Did you hear the latest news? | F84: 你聽到最新的新聞了嗎？ | G84: 30 | H84: 8 | I84: 105、106、107、108、109、111、112、114 | J84: 0.21 | K84: 33.65 | L84: A2 | M84: 1200單 | N84: (n.) 新聞 | O84: Other nouns | P84: ✓
A85: 84 | B85: bird | C85: =IFERROR(_xlfn.XLOOKUP(B85,'2000'!A:A,'2000'!B:B),"") -> bɝd | D85: (n.) 鳥 | E85: A bird flew past the window. | F85: 一隻鳥飛過窗戶。 | G85: 29 | H85: 6 | I85: 105、107、108、111、112、114 | J85: 0.203 | K85: 33.85 | L85: A1 | M85: 1200單 | N85: (n.) 鳥 | O85: Animals & insects | P85: ✓
A86: 85 | B86: move | C86: =IFERROR(_xlfn.XLOOKUP(B86,'2000'!A:A,'2000'!B:B),"") -> muv | D86: (v.) 移動 | E86: Please move the chair closer to the table. | F86: 請把椅子移得靠近桌子一點。 | G86: 29 | H86: 10 | I86: 105、106、107、108、109、110、111、112、113、114 | J86: 0.203 | K86: 34.05 | L86: 未分類 | M86: 1200單 | N86: (v.) 移動 | O86: Other verbs | P86: ✓
A87: 86 | B87: save | C87: =IFERROR(_xlfn.XLOOKUP(B87,'2000'!A:A,'2000'!B:B),"") -> sev | D87: (v.) 拯救 | E87: The firefighters saved the family from the fire. | F87: 消防員從火災中救出了那家人。 | G87: 29 | H87: 9 | I87: 105、106、107、108、109、110、112、113、114 | J87: 0.203 | K87: 34.25 | L87: 未分類 | M87: 1200單 | N87: (v.) 拯救 | O87: Other verbs | P87: ✓
A88: 87 | B88: word | C88: =IFERROR(_xlfn.XLOOKUP(B88,'2000'!A:A,'2000'!B:B),"") -> wɝd | D88: (n.) 字 | E88: Can you spell this word correctly? | F88: 你能正確拼寫這個字嗎？ | G88: 29 | H88: 7 | I88: 105、107、109、111、112、113、114 | J88: 0.203 | K88: 34.46 | L88: 未分類 | M88: 1200單 | N88: (n.) 字 | O88: Other nouns | P88: ✓
A89: 88 | B89: plan | C89: =IFERROR(_xlfn.XLOOKUP(B89,'2000'!A:A,'2000'!B:B),"") -> plæn | D89: (n.) 計畫 | E89: We need to make a plan for the project. | F89: 我們需要為這個項目制定一個計劃。 | G89: 29 | H89: 10 | I89: 105、106、107、108、109、110、111、112、113、114 | J89: 0.203 | K89: 34.66 | L89: A2 | M89: 1200單 | N89: (v.) 計劃；規劃 | O89: Other verbs | P89: ✓
A90: 89 | B90: coffee | C90: =IFERROR(_xlfn.XLOOKUP(B90,'2000'!A:A,'2000'!B:B),"") -> ˈkɔfɪ | D90: (n.) 咖啡 | E90: I drink coffee every morning. | F90: 我每天早上喝咖啡。 | G90: 29 | H90: 4 | I90: 105107108111 | J90: 0.203 | K90: 34.86 | L90: 未分類 | M90: 1200單 | N90: (n.) 咖啡 | O90: Food & drinks | P90: ✓
A91: 90 | B91: pay | C91: =IFERROR(_xlfn.XLOOKUP(B91,'2000'!A:A,'2000'!B:B),"") -> pe | D91: (v.) 付款 | E91: I’ll pay for dinner tonight. | F91: 我今晚請客吃飯。 | G91: 29 | H91: 8 | I91: 106、107、108、109、110、111、112、114 | J91: 0.203 | K91: 35.06 | L91: A1 | M91: 1200單 | N91: (v.) 付款 | O91: Money | P91: ✓
A92: 91 | B92: feel | C92: =IFERROR(_xlfn.XLOOKUP(B92,'2000'!A:A,'2000'!B:B),"") -> fil | D92: (v.) 感覺 | E92: I feel happy today. | F92: 我今天感覺很快樂。 | G92: 28 | H92: 9 | I92: 105、106、107、109、110、111、112、113、114 | J92: 0.196 | K92: 35.26 | L92: A1 | M92: 800單 | N92: (v.) 感覺；覺得 | O92: Other nouns | P92: ✓
A93: 92 | B93: report | C93: =IFERROR(_xlfn.XLOOKUP(B93,'2000'!A:A,'2000'!B:B),"") -> rɪˈport | D93: (n.) 報告 | E93: The teacher asked for a written report. | F93: 老師要求一份書面報告。 | G93: 28 | H93: 7 | I93: 105、106、108、110、111、112、113 | J93: 0.196 | K93: 35.46 | L93: A2 | M93: 1200單 | N93: (n.) 報告 | O93: Other nouns | P93: ✓
A94: 93 | B94: experience | C94: =IFERROR(_xlfn.XLOOKUP(B94,'2000'!A:A,'2000'!B:B),"") -> ɪkˈspɪrɪəns | D94: (n.) 經驗 | E94: Traveling gives you valuable life experiences. | F94: 旅行給你寶貴的人生經驗。 | G94: 28 | H94: 8 | I94: 105、106、108、109、110、112、113、114 | J94: 0.196 | K94: 35.65 | L94: A2 | M94: 1200單 | N94: (n.) 經驗 | O94: Other nouns | P94: ✓
A95: 94 | B95: enjoy | C95: =IFERROR(_xlfn.XLOOKUP(B95,'2000'!A:A,'2000'!B:B),"") -> ɪnˈdʒɔɪ | D95: (v.) 享受 | E95: I enjoy listening to music in my free time. | F95: 我喜歡在空閒時間聽音樂。 | G95: 27 | H95: 8 | I95: 105、108、109、110、111、112、113、114 | J95: 0.189 | K95: 36.04 | L95: A2 | M95: 1200單 | N95: (v.) 享受 | O95: Other verbs | P95: ✓
A96: 95 | B96: even | C96: =IFERROR(_xlfn.XLOOKUP(B96,'2000'!A:A,'2000'!B:B),"") -> ˈivən | D96: (adv.) 甚至 | E96: Even the best players can make mistakes. | F96: 即使是最優秀的球員也會犯錯。 | G96: 27 | H96: 9 | I96: 105、106、107、108、109、110、111、112、113 | J96: 0.189 | K96: 36.22 | L96: 未分類 | M96: 1200單 | N96: (adv.) 甚至 | O96: Other adverbs | P96: ✓
A97: 96 | B97: kind | C97: =IFERROR(_xlfn.XLOOKUP(B97,'2000'!A:A,'2000'!B:B),"") -> kaɪnd | D97: (adj.) 仁慈的 | E97: She is very kind to everyone. | F97: 她對每個人都非常仁慈。 | G97: 27 | H97: 8 | I97: 105、106、107、108、111、112、113、114 | J97: 0.189 | K97: 36.41 | L97: A1 | M97: 1200單 | N97: (adj.) 仁慈的 | O97: Personal characteristics | P97: ✓
A98: 97 | B98: enough | C98: =IFERROR(_xlfn.XLOOKUP(B98,'2000'!A:A,'2000'!B:B),"") -> ɪˈnʌf | D98: (adj.) 足夠的 | E98: Do we have enough food for everyone? | F98: 我們有足夠的食物給每一個人嗎？ | G98: 27 | H98: 9 | I98: 105、106、107、108、109、111、112、113、114 | J98: 0.189 | K98: 36.6 | L98: A1 | M98: 1200單 | N98: (adj.) 足夠的 | O98: Other adjectives | P98: ✓
A99: 98 | B99: use | C99: =IFERROR(_xlfn.XLOOKUP(B99,'2000'!A:A,'2000'!B:B),"") -> juz | D99: (v.) 使用 | E99: Can I use your pen? | F99: 我可以用你的筆嗎？ | G99: 27 | H99: 9 | I99: 105、106、107、109、110、111、112、113、114 | J99: 0.189 | K99: 36.79 | L99: 未分類 | M99: 1200單 | N99: (v.) 使用 | O99: Other verbs | P99: ✓
A100: 99 | B100: money | C100: =IFERROR(_xlfn.XLOOKUP(B100,'2000'!A:A,'2000'!B:B),"") -> ˈmʌnɪ | D100: (n.) 錢 | E100: How much money do you need? | F100: 你需要多少錢？ | G100: 27 | H100: 8 | I100: 105、106、107、109、110、111、113、114 | J100: 0.189 | K100: 36.98 | L100: A2 | M100: 1200單 | N100: (n.) 錢 | O100: Money | P100: ✓
A101: 100 | B101: important | C101: =IFERROR(_xlfn.XLOOKUP(B101,'2000'!A:A,'2000'!B:B),"") -> ɪmˈpɔrtənt | D101: (adj.) 重要的 | E101: This meeting is very important for the company. | F101: 這次會議對公司非常重要。 | G101: 27 | H101: 8 | I101: 105、107、108、109、111、112、113、114 | J101: 0.189 | K101: 37.17 | L101: 未分類 | M101: 1200單 | N101: (adj.) 重要的 | O101: Other adjectives | P101: ✓
A102: 101 | B102: call | C102: =IFERROR(_xlfn.XLOOKUP(B102,'2000'!A:A,'2000'!B:B),"") -> kɔl | D102: (n.) 呼叫 | E102: He received a call from his friend. | F102: 他接到朋友的電話。 | G102: 27 | H102: 8 | I102: 106、107、108、109、110、112、113、114 | J102: 0.189 | K102: 37.36 | L102: A1 | M102: 1200單 | N102: (v.) 打電話；呼叫 | O102: Other verbs | P102: ✓
... A107: 106 | B107: island | C107: =IFERROR(_xlfn.XLOOKUP(B107,'2000'!A:A,'2000'!B:B),"") -> ˈaɪlənd | D107: (n.) 島 | E107: Hawaii is a beautiful island. | F107: 夏威夷是一個美麗的島嶼。 | G107: 26 | H107: 6 | I107: 105、106、108、109、112、114 | J107: 0.182 | K107: 38.27 | L107: A2 | M107: 1200單 | N107: (n.) 島 | O107: Geographical terms | P107: ✓
A108: 107 | B108: whale | C108: =IFERROR(_xlfn.XLOOKUP(B108,'2000'!A:A,'2000'!B:B),"") -> hwel | D108: (n.) 鯨魚 | E108: Whales are the largest animals in the ocean. | F108: 鯨魚是海洋中最大的動物。 | G108: 26 | H108: 2 | I108: 105107 | J108: 0.182 | K108: 38.45 | L108: 未分類 | M108: 800單 | N108: (n.) 鯨魚 | O108: Animals & insects | P108: ✓
A109: 108 | B109: leave | C109: =IFERROR(_xlfn.XLOOKUP(B109,'2000'!A:A,'2000'!B:B),"") -> liv | D109: (v.) 離開 | E109: It’s time to leave for the airport. | F109: 是時候出發去機場了。 | G109: 26 | H109: 8 | I109: 105、106、108、109、110、111、112、113 | J109: 0.182 | K109: 38.63 | L109: 未分類 | M109: 1200單 | N109: (v.) 離開 | O109: Places-locations | P109: ✓
A110: 109 | B110: writer | C110: =IFERROR(_xlfn.XLOOKUP(B110,'2000'!A:A,'2000'!B:B),"") -> ˈraɪtɚ | D110: (n.) 作者 | E110: The writer signed copies of his new book. | F110: 這位作家簽名了他的新書副本。 | G110: 25 | H110: 7 | I110: 105、106、107、109、110、113、114 | J110: 0.175 | K110: 38.99 | L110: 未分類 | M110: 1200單 | N110: (n.) 作家 | O110: Occupations | P110: ✓
A111: 110 | B111: never | C111: =IFERROR(_xlfn.XLOOKUP(B111,'2000'!A:A,'2000'!B:B),"") -> ˈnɛvɚ | D111: (adv.) 從未 | E111: I have never been to Japan. | F111: 我從未去過日本。 | G111: 25 | H111: 8 | I111: 105、106、107、108、110、111、112、114 | J111: 0.175 | K111: 39.16 | L111: A1 | M111: 1200單 | N111: (adv.) 從未 | O111: Other adverbs | P111: ✓
A112: 111 | B112: week | C112: =IFERROR(_xlfn.XLOOKUP(B112,'2000'!A:A,'2000'!B:B),"") -> wik | D112: (n.) 週 | E112: There are seven days in a week. | F112: 一週有七天。 | G112: 25 | H112: 9 | I112: 105、106、107、108、109、110、111、113、114 | J112: 0.175 | K112: 39.33 | L112: A1 | M112: 1200單 | N112: (n.) 週 | O112: Time | P112: ✓
A113: 112 | B113: live | C113: =IFERROR(_xlfn.XLOOKUP(B113,'2000'!A:A,'2000'!B:B),"") -> lɪv | D113: (v.) 居住 | E113: She lives in New York City. | F113: 她住在紐約市。 | G113: 25 | H113: 9 | I113: 105、106、107、108、109、111、112、113、114 | J113: 0.175 | K113: 39.51 | L113: A1 | M113: 1200單 | N113: (v.) 居住 | O113: Family | P113: ✓
A114: 113 | B114: idea | C114: =IFERROR(_xlfn.XLOOKUP(B114,'2000'!A:A,'2000'!B:B),"") -> aɪˈdɪə | D114: (n.) 想法 | E114: I have an idea for our next project. | F114: 我對我們的下一個項目有一個想法。 | G114: 25 | H114: 9 | I114: 105、106、107、108、109、110、111、112、113 | J114: 0.175 | K114: 39.68 | L114: A1 | M114: 1200單 | N114: (n.) 想法 | O114: Other nouns | P114: ✓
A115: 114 | B115: still | C115: =IFERROR(_xlfn.XLOOKUP(B115,'2000'!A:A,'2000'!B:B),"") -> stɪl | D115: (adv.) 仍然 | E115: She is still waiting for the bus. | F115: 她仍在等公車。 | G115: 25 | H115: 9 | I115: 105、106、107、108、109、110、112、113、114 | J115: 0.175 | K115: 39.86 | L115: 未分類 | M115: 1200單 | N115: (adv.) 仍然 | O115: Other adverbs | P115: ✓
A116: 115 | B116: same | C116: =IFERROR(_xlfn.XLOOKUP(B116,'2000'!A:A,'2000'!B:B),"") -> sem | D116: (adj.) 相同的 | E116: We have the same opinion on this issue. | F116: 對於這個問題，我們意見相同。 | G116: 25 | H116: 8 | I116: 105、107、108、109、110、111、112、113 | J116: 0.175 | K116: 40.03 | L116: A1 | M116: 1200單 | N116: (adj.) 相同的 | O116: Other adjectives | P116: ✓
A117: 116 | B117: put | C117: =IFERROR(_xlfn.XLOOKUP(B117,'2000'!A:A,'2000'!B:B),"") -> pʊt | D117: (v.) 放置 | E117: Please put the book back on the shelf. | F117: 請把書放回書架上。 | G117: 25 | H117: 9 | I117: 106、107、108、109、110、111、112、113、114 | J117: 0.175 | K117: 40.21 | L117: 未分類 | M117: 1200單 | N117: (v.) 放置 | O117: Other verbs | P117: ✓
A118: 117 | B118: hard | C118: =IFERROR(_xlfn.XLOOKUP(B118,'2000'!A:A,'2000'!B:B),"") -> hɑrd | D118: (adj.) 難的 | E118: The test was very hard. | F118: 測驗非常難。 | G118: 24 | H118: 10 | I118: 105、106、107、108、109、110、111、112、113、114 | J118: 0.168 | K118: 40.38 | L118: A1 | M118: 1200單 | N118: (adj.) 難的 | O118: Other adjectives | P118: ✓
A119: 118 | B119: then | C119: =IFERROR(_xlfn.XLOOKUP(B119,'2000'!A:A,'2000'!B:B),"") -> ðɛn | D119: (adv.) 然後 | E119: We finished dinner, and then we watched TV. | F119: 我們吃完晚餐，然後看了電視。 | G119: 24 | H119: 10 | I119: 105、106、107、108、109、110、111、112、113、114 | J119: 0.168 | K119: 40.54 | L119: 未分類 | M119: 1200單 | N119: (adv.) 然後 | O119: Other adverbs | P119: ✓
A120: 119 | B120: during | C120: =IFERROR(_xlfn.XLOOKUP(B120,'2000'!A:A,'2000'!B:B),"") -> ˈdjʊrɪŋ | D120: (prep.) 在…期間 | E120: During the meeting, we discussed the new plan. | F120: 在會議期間，我們討論了新計劃。 | G120: 24 | H120: 8 | I120: 105、107、108、109、110、111、113、114 | J120: 0.168 | K120: 40.71 | L120: A2 | M120: 1200單 | N120: (prep.) 在…期間 | O120: Prepositions | P120: ✓
... A126: 125 | B126: lot | C126: =IFERROR(_xlfn.XLOOKUP(B126,'2000'!A:A,'2000'!B:B),"") -> lɑt | D126: (n.) 許多 | E126: Thanks a lot for your help! | F126: 非常感謝你的幫助！ | G126: 23 | H126: 9 | I126: 106、107、108、109、110、111、112、113、114 | J126: 0.161 | K126: 41.7 | L126: 未分類 | M126: 1200單 | N126: (n.) 許多；大量 | O126: Numbers | P126: ✓
A127: 126 | B127: card | C127: =IFERROR(_xlfn.XLOOKUP(B127,'2000'!A:A,'2000'!B:B),"") -> kɑrd | D127: (n.) 卡片 | E127: She sent me a birthday card. | F127: 她寄給我一張生日卡片。 | G127: 22 | H127: 5 | I127: 105106110113114 | J127: 0.154 | K127: 42.33 | L127: 未分類 | M127: 1200單 | N127: (n.) 卡片 | O127: Sports, interests-hobbies | P127: ✓
A128: 127 | B128: shake | C128: =IFERROR(_xlfn.XLOOKUP(B128,'2000'!A:A,'2000'!B:B),"") -> ʃek | D128: (v.) 搖動 | E128: Shake the bottle before using it. | F128: 使用前搖晃瓶子。 | G128: 22 | H128: 4 | I128: 105107110112 | J128: 0.154 | K128: 42.49 | L128: 未分類 | M128: 1200單 | N128: (v.) 搖動 | O128: Other verbs | P128: ✓
A129: 128 | B129: class | C129: =IFERROR(_xlfn.XLOOKUP(B129,'2000'!A:A,'2000'!B:B),"") -> klæs | D129: (n.) 班級 | E129: She is in my math class. | F129: 她在我的數學班上。 | G129: 21 | H129: 8 | I129: 105、106、108、109、111、112、113、114 | J129: 0.147 | K129: 42.79 | L129: 未分類 | M129: 1200單 | N129: (n.) 班級 | O129: School | P129: ✓
A130: 129 | B130: world | C130: =IFERROR(_xlfn.XLOOKUP(B130,'2000'!A:A,'2000'!B:B),"") -> wɝld | D130: (n.) 世界 | E130: The world is full of amazing places to explore. | F130: 世界上充滿了值得探索的奇妙地方。 | G130: 21 | H130: 9 | I130: 105、106、107、108、109、110、111、112、113 | J130: 0.147 | K130: 42.93 | L130: A1 | M130: 800單 | N130: (n.) 世界 | O130: Countries-and-areas | P130: ✓
A131: 130 | B131: house | C131: =IFERROR(_xlfn.XLOOKUP(B131,'2000'!A:A,'2000'!B:B),"") -> haʊs | D131: (n.) 房子 | E131: Their house is near the park. | F131: 他們的房子靠近公園。 | G131: 21 | H131: 7 | I131: 105、107、110、111、112、113、114 | J131: 0.147 | K131: 43.08 | L131: A1 | M131: 1200單 | N131: (n.) 房子 | O131: Houses-apartments | P131: ✓
A132: 131 | B132: around | C132: =IFERROR(_xlfn.XLOOKUP(B132,'2000'!A:A,'2000'!B:B),"") -> əˈraʊnd | D132: (adv.) 在附近 | E132: There are many shops around here. | F132: 這附近有很多商店。 | G132: 21 | H132: 8 | I132: 105、106、107、110、111、112、113、114 | J132: 0.147 | K132: 43.23 | L132: 未分類 | M132: 1200單 | N132: (adv.) 在附近 | O132: Prepositions | P132: ✓
A133: 132 | B133: stay | C133: =IFERROR(_xlfn.XLOOKUP(B133,'2000'!A:A,'2000'!B:B),"") -> ste | D133: (v.) 停留 | E133: We stayed at the hotel for three nights. | F133: 我們在飯店住了三晚。 | G133: 21 | H133: 9 | I133: 105、106、107、109、110、111、112、113、114 | J133: 0.147 | K133: 43.37 | L133: A1 | M133: 1200單 | N133: (v.) 停留 | O133: Other verbs | P133: ✓
A134: 133 | B134: sell | C134: =IFERROR(_xlfn.XLOOKUP(B134,'2000'!A:A,'2000'!B:B),"") -> sɛl | D134: (v.) 販賣 | E134: They sell fresh vegetables at the market. | F134: 他們在市場上賣新鮮蔬菜。 | G134: 21 | H134: 8 | I134: 105、106、107、109、110、111、113、114 | J134: 0.147 | K134: 43.52 | L134: A1 | M134: 1200單 | N134: (v.) 販賣 | O134: Other verbs | P134: ✓
A135: 134 | B135: few | C135: =IFERROR(_xlfn.XLOOKUP(B135,'2000'!A:A,'2000'!B:B),"") -> fju | D135: (adj.) 少數的 | E135: Only a few people attended the meeting. | F135: 只有少數人參加了會議。 | G135: 21 | H135: 9 | I135: 105、106、108、109、110、111、112、113、114 | J135: 0.147 | K135: 43.81 | L135: A2 | M135: 1200單 | N135: (adj.) 一些 | O135: Numbers | P135: ✓
A136: 135 | B136: into | C136: =IFERROR(_xlfn.XLOOKUP(B136,'2000'!A:A,'2000'!B:B),"") -> ˈɪntʊ | D136: (prep.) 進入…之內 | E136: He walked into the room quietly. | F136: 他靜靜地走進房間。 | G136: 21 | H136: 8 | I136: 105、106、107、108、109、110、111、113 | J136: 0.147 | K136: 43.96 | L136: 未分類 | M136: 1200單 | N136: (prep.) 進入…之內 | O136: Prepositions | P136: ✓
A137: 136 | B137: chance | C137: =IFERROR(_xlfn.XLOOKUP(B137,'2000'!A:A,'2000'!B:B),"") -> tʃæns | D137: (n.) 機會 | E137: You have a good chance to win the game. | F137: 你有很好的機會贏得比賽。 | G137: 21 | H137: 7 | I137: 106、107、109、110、111、112、113 | J137: 0.147 | K137: 44.11 | L137: 未分類 | M137: 1200單 | N137: (n.) 機會 | O137: Other nouns | P137: ✓
A138: 137 | B138: park | C138: =IFERROR(_xlfn.XLOOKUP(B138,'2000'!A:A,'2000'!B:B),"") -> pɑrk | D138: (n.) 公園 | E138: We went for a walk in the park. | F138: 我們去公園散步了。 | G138: 21 | H138: 4 | I138: 107110112113 | J138: 0.147 | K138: 44.25 | L138: A1 | M138: 1200單 | N138: (n.) 公園 | O138: Places-locations | P138: ✓
A139: 138 | B139: happy | C139: =IFERROR(_xlfn.XLOOKUP(B139,'2000'!A:A,'2000'!B:B),"") -> ˈhæpɪ | D139: (adj.) 快樂的 | E139: She felt happy after receiving the gift. | F139: 收到禮物後，她感到很快樂。 | G139: 20 | H139: 8 | I139: 105、107、108、109、110、111、113、114 | J139: 0.14 | K139: 44.69 | L139: A1 | M139: 1200單 | N139: (adj.) 快樂的 | O139: Personal characteristics | P139: ✓
A140: 139 | B140: down | C140: =IFERROR(_xlfn.XLOOKUP(B140,'2000'!A:A,'2000'!B:B),"") -> daʊn | D140: (adv.) 向下 | E140: The ball rolled down the hill. | F140: 球滾下了山坡。 | G140: 20 | H140: 7 | I140: 105、106、107、108、110、113、114 | J140: 0.14 | K140: 45.11 | L140: A2 | M140: 1200單 | N140: (adv.) 向下 | O140: Prepositions | P140: ✓
A141: 140 | B141: sun | C141: =IFERROR(_xlfn.XLOOKUP(B141,'2000'!A:A,'2000'!B:B),"") -> sʌn | D141: (n.) 太陽 | E141: The sun rises in the east. | F141: 太陽從東方升起。 | G141: 20 | H141: 6 | I141: 105、106、107、109、111、112 | J141: 0.14 | K141: 45.25 | L141: A1 | M141: 1200單 | N141: (n.) 太陽 | O141: Weather-nature | P141: ✓
A142: 141 | B142: TRUE | C142: =IFERROR(_xlfn.XLOOKUP(B142,'2000'!A:A,'2000'!B:B),"") -> tru | D142: (adj.) 真的 | E142: Is the story true? | F142: 這個故事是真的嗎？ | G142: 20 | H142: 9 | I142: 105、106、107、108、109、110、111、112、114 | J142: 0.14 | K142: 45.39 | L142: 未分類 | M142: 1200單 | N142: (adj.) 真的 | O142: Other adjectives | P142: ✓
A143: 142 | B143: example | C143: =IFERROR(_xlfn.XLOOKUP(B143,'2000'!A:A,'2000'!B:B),"") -> ɪɡˈzæmpl | D143: (n.) 例子 | E143: Can you give me an example of what you mean? | F143: 你能舉個例子說明你的意思嗎？ | G143: 20 | H143: 8 | I143: 105、107、109、110、111、112、113、114 | J143: 0.14 | K143: 45.53 | L143: A1 | M143: 1200單 | N143: (n.) 例子 | O143: School | P143: ✓
A144: 143 | B144: library | C144: =IFERROR(_xlfn.XLOOKUP(B144,'2000'!A:A,'2000'!B:B),"") -> ˈlaɪˌbrɛrɪ | D144: (n.) 圖書館 | E144: I borrowed a book from the library yesterday. | F144: 我昨天從圖書館借了一本書。 | G144: 20 | H144: 6 | I144: 106、107、109、110、111、113 | J144: 0.14 | K144: 45.67 | L144: 未分類 | M144: 1200單 | N144: (n.) 圖書館 | O144: School | P144: ✓
A145: 144 | B145: baby | C145: =IFERROR(_xlfn.XLOOKUP(B145,'2000'!A:A,'2000'!B:B),"") -> ˈbebɪ | D145: (n.) 嬰兒 | E145: The baby is sleeping soundly. | F145: 嬰兒睡得很香。 | G145: 20 | H145: 6 | I145: 107、108、110、112、113、114 | J145: 0.14 | K145: 45.81 | L145: A1 | M145: 1200單 | N145: (n.) 嬰兒 | O145: People | P145: ✓
A146: 145 | B146: tree | C146: =IFERROR(_xlfn.XLOOKUP(B146,'2000'!A:A,'2000'!B:B),"") -> tri | D146: (n.) 樹 | E146: The tree provides shade in the summer. | F146: 這棵樹在夏天提供陰涼。 | G146: 20 | H146: 5 | I146: 107108109110114 | J146: 0.14 | K146: 45.95 | L146: A1 | M146: 1200單 | N146: (n.) 樹 | O146: Other nouns | P146: ✓
A147: 146 | B147: worker | C147: =IFERROR(_xlfn.XLOOKUP(B147,'2000'!A:A,'2000'!B:B),"") -> ˈwɝkɚ | D147: (n.) 工人 | E147: The workers finished building the house on time. | F147: 工人們按時完成了房子的建造。 | G147: 20 | H147: 3 | I147: 111113114 | J147: 0.14 | K147: 46.23 | L147: 未分類 | M147: 1200單 | N147: (n.) 工人 | O147: Occupations | P147: ✓
A148: 147 | B148: care | C148: =IFERROR(_xlfn.XLOOKUP(B148,'2000'!A:A,'2000'!B:B),"") -> kɛr | D148: (v.) 關心 | E148: You should care about your health. | F148: 你應該關心你的健康。 | G148: 19 | H148: 9 | I148: 105、106、107、108、109、110、111、112、114 | J148: 0.133 | K148: 46.5 | L148: A1 | M148: 1200單 | N148: (v.) 關心 | O148: Other verbs | P148: ✓
A149: 148 | B149: hurt | C149: =IFERROR(_xlfn.XLOOKUP(B149,'2000'!A:A,'2000'!B:B),"") -> hɝt | D149: (v.) 受傷 | E149: Be careful not to hurt yourself. | F149: 小心別傷到自己。 | G149: 19 | H149: 8 | I149: 105、106、108、109、111、112、113、114 | J149: 0.133 | K149: 46.63 | L149: 未分類 | M149: 1200單 | N149: (v.) 受傷 | O149: Other verbs | P149: ✓
A150: 149 | B150: summer | C150: =IFERROR(_xlfn.XLOOKUP(B150,'2000'!A:A,'2000'!B:B),"") -> ˈsʌmɚ | D150: (n.) 夏天 | E150: I love swimming in the summer. | F150: 我喜歡夏天游泳。 | G150: 19 | H150: 8 | I150: 105、107、109、110、111、112、113、114 | J150: 0.133 | K150: 46.76 | L150: A1 | M150: 1200單 | N150: (n.) 夏天 | O150: Time | P150: ✓
A151: 150 | B151: surprise | C151: =IFERROR(_xlfn.XLOOKUP(B151,'2000'!A:A,'2000'!B:B),"") -> sɚˈpraɪz | D151: (v.) 驚訝 | E151: Her visit surprised me. | F151: 她的到訪讓我感到驚訝。 | G151: 19 | H151: 9 | I151: 105、106、107、108、109、110、112、113、114 | J151: 0.133 | K151: 46.9 | L151: 未分類 | M151: 1200單 | N151: (v.) 使驚訝；給…驚喜 | O151: Other verbs | P151: ✓
A152: 151 | B152: cook | C152: =IFERROR(_xlfn.XLOOKUP(B152,'2000'!A:A,'2000'!B:B),"") -> kʊk | D152: (v.) 煮 | E152: She cooked dinner for the family. | F152: 她為家人煮了晚餐。 | G152: 19 | H152: 7 | I152: 105、107、108、110、112、113、114 | J152: 0.133 | K152: 47.03 | L152: A2 | M152: 1200單 | N152: (v.) 煮 | O152: Food & drinks | P152: ✓
A153: 152 | B153: festival | C153: =IFERROR(_xlfn.XLOOKUP(B153,'2000'!A:A,'2000'!B:B),"") -> ˈfɛstɪvl | D153: (n.) 節慶 | E153: We celebrate the Spring Festival with our family. | F153: 我們與家人一起慶祝春節。 | G153: 19 | H153: 4 | I153: 106109110113 | J153: 0.133 | K153: 47.43 | L153: 未分類 | M153: 1200單 | N153: (n.) 節慶 | O153: Holidays & festivals | P153: ✓
A154: 153 | B154: morning | C154: =IFERROR(_xlfn.XLOOKUP(B154,'2000'!A:A,'2000'!B:B),"") -> ˈmɔrnɪŋ | D154: (n.) 早上 | E154: Today is a beautiful morning. | F154: 今天是一個美好的早晨。 | G154: 19 | H154: 6 | I154: 107、108、109、111、112、114 | J154: 0.133 | K154: 47.56 | L154: A1 | M154: 1200單 | N154: (n.) 早上 | O154: Time | P154: ✓
A155: 154 | B155: chocolate | C155: =IFERROR(_xlfn.XLOOKUP(B155,'2000'!A:A,'2000'!B:B),"") -> ˈtʃɔklɪt | D155: (n.) 巧克力 | E155: I bought some chocolate for dessert. | F155: 我買了一些巧克力當甜點。 | G155: 19 | H155: 3 | I155: 109111114 | J155: 0.133 | K155: 47.69 | L155: 未分類 | M155: 1200單 | N155: (n.) 巧克力 | O155: Food & drinks | P155: ✓
A156: 155 | B156: war | C156: =IFERROR(_xlfn.XLOOKUP(B156,'2000'!A:A,'2000'!B:B),"") -> wɔr | D156: (n.) 戰爭 | E156: The war caused a lot of destruction. | F156: 戰爭造成了很多破壞。 | G156: 19 | H156: 3 | I156: 110112113 | J156: 0.133 | K156: 47.83 | L156: 未分類 | M156: 800單 | N156: (n.) 戰爭 | O156: Other nouns | P156: ✓
A157: 156 | B157: birthday | C157: =IFERROR(_xlfn.XLOOKUP(B157,'2000'!A:A,'2000'!B:B),"") -> ˈbɝθˌde | D157: (n.) 生日 | E157: Today is my birthday! | F157: 今天是我的生日！ | G157: 18 | H157: 8 | I157: 105、106、108、109、110、111、112、114 | J157: 0.126 | K157: 47.95 | L157: A1 | M157: 1200單 | N157: (n.) 生日 | O157: Other nouns | P157: ✓
A158: 157 | B158: parent | C158: =IFERROR(_xlfn.XLOOKUP(B158,'2000'!A:A,'2000'!B:B),"") -> ˈpɛrənt | D158: (n.) 父親(或母親) | E158: My parents are coming to visit me this weekend. | F158: 我父母這個週末要來看我。 | G158: 18 | H158: 8 | I158: 105、106、107、108、110、112、113、114 | J158: 0.126 | K158: 48.08 | L158: 未分類 | M158: 1200單 | N158: (n.) 父母 | O158: Family | P158: ✓
A159: 158 | B159: next | C159: =IFERROR(_xlfn.XLOOKUP(B159,'2000'!A:A,'2000'!B:B),"") -> nɛkst | D159: (adj.) 下一個的 | E159: What are you doing next weekend? | F159: 你下週末打算做什麼？ | G159: 18 | H159: 9 | I159: 105、106、107、108、109、110、112、113、114 | J159: 0.126 | K159: 48.2 | L159: A1 | M159: 1200單 | N159: (adj.) 下一個的 | O159: Time | P159: ✓
A160: 159 | B160: worry | C160: =IFERROR(_xlfn.XLOOKUP(B160,'2000'!A:A,'2000'!B:B),"") -> ˈwɝɪ | D160: (v.) 擔心 | E160: Don’t worry; everything will be fine. | F160: 別擔心，一切都會好起來的。 | G160: 18 | H160: 9 | I160: 105、106、107、108、109、110、111、112、113 | J160: 0.126 | K160: 48.33 | L160: 未分類 | M160: 1200單 | N160: (v.) 擔心 | O160: Other verbs | P160: ✓
A161: 160 | B161: white | C161: =IFERROR(_xlfn.XLOOKUP(B161,'2000'!A:A,'2000'!B:B),"") -> hwaɪt | D161: (adj.) 白色的 | E161: She wore a white dress to the party. | F161: 她穿了一件白色連衣裙去參加派對。 | G161: 18 | H161: 5 | I161: 105110112113114 | J161: 0.126 | K161: 48.46 | L161: A1 | M161: 1200單 | N161: (adj.) 白色的 | O161: Colors | P161: ✓
A162: 161 | B162: english | C162: =IFERROR(_xlfn.XLOOKUP(B162,'2000'!A:A,'2000'!B:B),"") -> ˈɪŋɡlɪʃ | D162: n. 英語 | E162: She is learning English as a second language. | F162: 她正在把英語作為第二語言學習。 | G162: 18 | H162: 5 | I162: 105106108111112 | J162: 0.126 | K162: 48.58 | L162: 未分類 | M162: 1200單 | N162: (n.) 英語 | O162: Languages | P162: ✓
A163: 162 | B163: really | C163: =IFERROR(_xlfn.XLOOKUP(B163,'2000'!A:A,'2000'!B:B),"") -> ˈrɪəlɪ | D163: (adv.) 真實地 | E163: I really enjoyed the movie. | F163: 我真的很喜歡這部電影。 | G163: 18 | H163: 8 | I163: 105、106、107、110、111、112、113、114 | J163: 0.126 | K163: 48.71 | L163: A1 | M163: 1200單 | N163: (adv.) 真的；非常 | O163: Other adverbs | P163: ✓
A164: 163 | B164: little | C164: =IFERROR(_xlfn.XLOOKUP(B164,'2000'!A:A,'2000'!B:B),"") -> ˈlɪtl | D164: (adj.) 少的 | E164: There is little time left before the deadline. | F164: 截止日期前幾乎沒有時間了。 | G164: 18 | H164: 7 | I164: 105、106、107、109、111、112、113 | J164: 0.126 | K164: 48.83 | L164: A1 | M164: 1200單 | N164: (adj./adv.) 少量的；一點 | O164: Numbers | P164: ✓
A165: 164 | B165: between | C165: =IFERROR(_xlfn.XLOOKUP(B165,'2000'!A:A,'2000'!B:B),"") -> bɪˈtwin | D165: (prep.) 在…之間 | E165: The library is between the school and the park. | F165: 圖書館在學校和公園之間。 | G165: 18 | H165: 6 | I165: 106、108、109、110、111、113 | J165: 0.126 | K165: 48.96 | L165: A1 | M165: 1200單 | N165: (prep.) 在…之間 | O165: Prepositions | P165: ✓
...

Sheet 2000
A1: 英文 | B1: KK音標 | C1: 中譯 | D1: 例句 | E1: 翻譯 | F1: 詞性
A2: able | B2: ˈebl | C2: (adj.) 有能力的 | D2: He is able to solve the problem. | E2: 他有能力解決這個問題。 | F2: 形容詞
A3: about | B3: əˈbaʊt | C3: (prep.) 有關 | D3: This book is about history. | E3: 這本書是關於歷史的。 | F3: 介系詞
A4: above | B4: əˈbʌv | C4: (adv.) 在上方 | D4: The bird flew above the tree. | E4: 鳥兒飛過了樹的上方。 | F4: 副詞
A5: abroad | B5: əˈbrɔd | C5: (adv.) 在國外 | D5: She is studying abroad this year. | E5: 她今年正在國外學習。 | F5: 副詞
A6: absent | B6: ˈæbsənt | C6: (adj.) 缺席的 | D6: John was absent from the meeting yesterday. | E6: 約翰昨天缺席了會議。 | F6: 形容詞
A7: accept | B7: əkˈsɛpt | C7: (v.) 接受 | D7: I can't accept your gift. | E7: 我不能接受你的禮物。 | F7: 動詞
A8: accident | B8: ˈæksədənt | C8: (n.) 意外 | D8: There was a car accident on the highway. | E8: 高速公路上發生了一起車禍。 | F8: 名詞
A9: across | B9: əˈkrɔs | C9: (prep.) 在…對面 | D9: The park is across the street. | E9: 公園在街的對面。 | F9: 介系詞
A10: act | B10: ækt | C10: (n.) 行為 | D10: His act of kindness touched everyone. | E10: 他的善舉感動了每一個人。 | F10: 名詞
A11: action | B11: ˈækʃən | C11: (n.) 活動 | D11: The government took action to improve education. | E11: 政府採取行動改善教育。 | F11: 名詞
A12: active | B12: ˈæktɪv | C12: (adj.) 積極的 | D12: She is an active member of the club. | E12: 她是俱樂部的一名積極成員。 | F12: 形容詞
... A623: fall | B623: fɔl | C623: (v.) 倒下 | D623: The tree fell during the storm. | E623: 樹在暴風雨中倒下了。 | F623: 動詞
A624: FALSE | B624: fɔls | C624: (adj.) 錯的 | D624: The answer is false; you need to correct it. | E624: 答案是錯的，你需要改正它。 | F624: 形容詞
A625: family | B625: ˈfæməlɪ | C625: (n.) 家 | D625: My family is very supportive. | E625: 我的家庭非常支持我。 | F625: 名詞
A626: famous | B626: ˈfeməs | C626: (adj.) 著名的 | D626: This actor is famous all over the world. | E626: 這位演員舉世聞名。 | F626: 形容詞
A627: fan | B627: fæn | C627: (n.) 電扇 | D627: Turn on the fan, it’s getting hot. | E627: 打開電扇，天氣越來越熱了。 | F627: 名詞
A628: fancy | B628: ˈfænsɪ | C628: (n.) 想像力 | D628: Her imagination is full of fancy ideas. | E628: 她的想像力充滿了奇妙的想法。 | F628: 名詞
A629: fantastic | B629: fænˈtæstɪk | C629: (adj.) 極好的 | D629: The movie was absolutely fantastic! | E629: 這部電影簡直棒極了！ | F629: 形容詞
A630: far | B630: fɑr | C630: (adj.) 遠方的 | D630: The beach is far from here. | E630: 海灘離這裡很遠。 | F630: 形容詞
A631: farm | B631: fɑrm | C631: (n.) 農場 | D631: They live on a farm in the countryside. | E631: 他們住在鄉下的農場。 | F631: 名詞
A632: farmer | B632: ˈfɑrmɚ | C632: (n.) 農夫 | D632: The farmer grows wheat and corn. | E632: 這位農夫種植小麥和玉米。 | F632: 名詞
A633: fashion | B633: ˈfæʃən | C633: (n.) 流行 | D633: She always follows the latest fashion trends. | E633: 她總是追隨最新的時尚潮流。 | F633: 名詞
A634: fast | B634: fæst | C634: (adj.) 快的 | D634: The car is very fast. | E634: 這輛車非常快。 | F634: 形容詞
A635: fat | B635: fæt | C635: (adj.) 肥胖的 | D635: Eating too much junk food can make you fat. | E635: 吃太多垃圾食品會讓你變胖。 | F635: 形容詞
A636: father | B636: ˈfɑðɚ | C636: (n.) 父親 | D636: My father is a teacher. | E636: 我父親是一名教師。 | F636: 名詞
... A1510: scare | B1510: skɛr | C1510: (v.) (使)害怕 | D1510: The loud noise scared the children. | E1510: 大聲的噪音嚇到了孩子們。 | F1510: 動詞
A1511: scared | B1511: skɛrd | C1511: (adj.) 驚恐的
A1512: scarf | B1512: skɑrf | C1512: (n.) 圍巾 | D1512: She wore a warm scarf to protect herself from the cold. | E1512: 她圍上一條暖和的圍巾以防寒。 | F1512: 名詞
A1513: scene | B1513: sin | C1513: (n.) 風景 | D1513: The sunset created a beautiful scene. | E1513: 日落創造了一幅美麗的景象。 | F1513: 名詞
A1514: scenery | B1514: ˈsinərɪ | C1514: (n.) 景色 | D1514: The mountain scenery was breathtaking. | E1514: 山區的景色令人驚嘆。 | F1514: 名詞
A1515: school | B1515: skul | C1515: (n.) 學校 | D1515: She goes to school every day. | E1515: 她每天去上學。 | F1515: 名詞
A1516: science | B1516: ˈsaɪəns | C1516: (n.) 科學 | D1516: Science helps us understand the world. | E1516: 科學幫助我們了解世界。 | F1516: 名詞
A1517: scientist | B1517: ˈsaɪəntɪst | C1517: (n.) 科學家 | D1517: The scientist conducted an experiment in the lab. | E1517: 科學家在實驗室進行了一項實驗。 | F1517: 名詞
A1518: scooter | B1518: ˈskutɚ | C1518: (n.) 摩托車 | D1518: He rides a scooter to work every day. | E1518: 他每天騎摩托車上班。 | F1518: 名詞
A1519: score | B1519: skɔr | C1519: (n.) 得分 | D1519: The team scored three goals in the match. | E1519: 球隊在比賽中得了三分。 | F1519: 名詞
A1520: screen | B1520: skrin | C1520: (n.) 螢幕 | D1520: The movie was shown on a large screen. | E1520: 電影在大螢幕上放映。 | F1520: 名詞
A1521: sculpture | B1521: ˈskʌlptʃɚ | C1521: n. 雕塑 | D1521: The artist created a beautiful sculpture. | E1521: 藝術家創作了一件美麗的雕塑。 | F1521: 名詞
A1522: sea | B1522: si | C1522: (n.) 海 | D1522: The sea looks calm today. | E1522: 今天海面看起來很平靜。 | F1522: 名詞
A1523: seafood | B1523: ˈsiˌfud | C1523: (n.) 海鮮 | D1523: I love eating seafood at the restaurant. | E1523: 我喜歡在餐廳吃海鮮。 | F1523: 名詞
... A1878: truck | B1878: trʌk | C1878: (n.) 卡車 | D1878: The truck delivered goods to the store. | E1878: 卡車把貨物送到商店。 | F1878: 名詞
A1879: TRUE | B1879: tru | C1879: (adj.) 真的 | D1879: Is the story true? | E1879: 這個故事是真的嗎？ | F1879: 形容詞
A1880: trumpet | B1880: ˈtrʌmpɪt | C1880: (n.) 喇叭 | D1880: He plays the trumpet in the school band. | E1880: 他在學校樂隊裡吹喇叭。 | F1880: 名詞
A1881: trust | B1881: trʌst | C1881: (v.) 相信 | D1881: You can trust me; I won’t tell anyone. | E1881: 你可以相信我，我不會告訴任何人。 | F1881: 動詞
A1882: truth | B1882: truθ | C1882: (n.) 事實 | D1882: Tell me the truth about what happened. | E1882: 告訴我發生了什麼事的真相。 | F1882: 名詞
A1883: try | B1883: traɪ | C1883: (v.) 試圖 | D1883: I’ll try my best to finish the project on time. | E1883: 我會盡力按時完成這個項目。 | F1883: 動詞
A1884: tube | B1884: tjub | C1884: (n.) 管子 | D1884: The toothpaste comes in a small tube. | E1884: 牙膏裝在一個小管子裡。 | F1884: 名詞
A1885: Tuesday | B1885: ˈtjuzde | C1885: (n.) 星期二 | D1885: We have a meeting every Tuesday. | E1885: 我們每週二都有會議。 | F1885: 名詞
A1886: tunnel | B1886: ˈtʌnl | C1886: (n.) 隧道 | D1886: The train passed through the tunnel. | E1886: 火車穿過了隧道。 | F1886: 名詞
A1887: turkey | B1887: ˈtɝkɪ | C1887: (n.) 火雞 | D1887: We had roast turkey for Thanksgiving dinner. | E1887: 我們感恩節晚餐吃了烤火雞。 | F1887: 名詞
A1888: turn | B1888: tɝn | C1888: (v.) 轉彎 | D1888: Turn left at the next corner. | E1888: 在下一個街角向左轉。 | F1888: 動詞
A1889: turtle | B1889: ˈtɝtl | C1889: (n.) 烏龜 | D1889: The turtle moved slowly across the road. | E1889: 烏龜慢慢地爬過馬路。 | F1889: 名詞
A1890: twelve | B1890: twɛlv | C1890: (n.) 十二 | D1890: There are twelve months in a year. | E1890: 一年有十二個月。 | F1890: 名詞
A1891: twenty | B1891: ˈtwɛntɪ | C1891: (n.) 二十 | D1891: She turned twenty last week. | E1891: 她上週滿二十歲。 | F1891: 名詞
... A2030: zoo | B2030: zu | C2030: (n.) 動物園 | D2030: We visited the zoo and saw many animals. | E2030: 我們參觀了動物園，看到了許多動物。 | F2030: 名詞
A2031: American | B2031: əˈmɛrɪkən | C2031: (adj.) 美國的 (n.) 美國人 | D2031: He is an American teacher. | E2031: 他是一位美國老師。
A2032: Taiwanese | B2032: ˌtaɪwɑˈniz | C2032: (n.) 台灣人 (adj.) 台灣的 | D2032: I like Taiwanese food. | E2032: 我喜歡台灣食物。
A2033: beside | B2033: bɪˈsaɪd | C2033: (prep.) 在…旁邊 | D2033: The pen is beside the book. | E2033: 筆在書本旁邊。
A2034: Taiwan | B2034: ˈtaɪˈwɑn | C2034: (n.) 臺灣 | D2034: I live in Taiwan. | E2034: 我住在台灣。
A2035: sometime | B2035: ˈsʌmˌtaɪm | C2035: (adv.) 在某個時候 | D2035: Let’s see a movie sometime. | E2035: 我們找個時間看電影吧。
A2036: comic | B2036: ˈkɑmɪk | C2036: (adj.) 喜劇的 | D2036: My brother likes comic books. | E2036: 我哥哥喜歡漫畫書。
A2037: hey | B2037: he | C2037: 嗨；嘿 | D2037: Hey, how are you today? | E2037: 嘿，你今天好嗎？
A2038: bookstore | B2038: ˈbʊkˌstɔr | C2038: (n.) 書店 | D2038: I go to the bookstore every Sunday. | E2038: 我每個星期天都去書店。
A2039: boring | B2039: ˈbɔrɪŋ | C2039: (adj.) 無聊的，無趣的 | D2039: This game is boring. | E2039: 這個遊戲很無聊。
A2040: metro | B2040: ˈmɛtro | C2040: (n.) 地鐵 | D2040: I take the metro to work. | E2040: 我搭捷運去上班。
A2041: cloth | B2041: klɔθ | C2041: (n.) 布 | D2041: Use this cloth to clean the table. | E2041: 用這塊布來擦桌子。
A2042: Chinese | B2042: ˌtʃaɪˈniz | C2042: (adj.) 中國的 (n.) 中文，中國人 | D2042: Can you speak Chinese? | E2042: 你會說中文嗎？
... A2059: Japanese | B2059: ˌdʒæpəˈniz | C2059: (adj.) 日本的 (n.) 日本人，日文 | D2059: I like Japanese animation. | E2059: 我喜歡日本動漫。
A2060: sunshine | B2060: ˈsʌnˌʃaɪn | C2060: (n.) 陽光
